LICENSE
setup.cfg
setup.py
pyasyncmysql/__init__.py
pyasyncmysql/config.py
pyasyncmysql/db.py
pyasyncmysql.egg-info/PKG-INFO
pyasyncmysql.egg-info/SOURCES.txt
pyasyncmysql.egg-info/dependency_links.txt
pyasyncmysql.egg-info/not-zip-safe
pyasyncmysql.egg-info/top_level.txt