Metadata-Version: 2.1
Name: pyasyncmysql
Version: 0.1.1
Summary: Async Python library for simple & fast async MySQL operations
Author-email: edm.rud3nko@yandex.ru
License-File: LICENSE
